mentor/__init__.py
mentor/admin.py
mentor/apps.py
mentor/forms.py
mentor/models.py
mentor/urls.py
mentor/views.py
mentor/static/mentor/js/main.js
mentor/static/mentor/scss/_footer.scss
mentor/static/mentor/scss/_general.scss
mentor/static/mentor/scss/_header.scss
mentor/static/mentor/scss/_hero.scss
mentor/static/mentor/scss/_nav.scss
mentor/static/mentor/scss/_sections.scss
mentor/static/mentor/scss/_variables_eng.scss
mentor/static/mentor/scss/_variables_kor.scss
mentor/static/mentor/scss/style_eng.scss
mentor/static/mentor/scss/style_kor.scss
mentor/static/mentor/vendor/animate.css/animate.compat.css
mentor/static/mentor/vendor/animate.css/animate.css
mentor/static/mentor/vendor/animate.css/animate.min.css
mentor/static/mentor/vendor/aos/aos.css
mentor/static/mentor/vendor/aos/aos.js
mentor/static/mentor/vendor/bootstrap/css/bootstrap-grid.css
mentor/static/mentor/vendor/bootstrap/css/bootstrap-grid.css.map
mentor/static/mentor/vendor/bootstrap/css/bootstrap-grid.min.css
mentor/static/mentor/vendor/bootstrap/css/bootstrap-grid.min.css.map
mentor/static/mentor/vendor/bootstrap/css/bootstrap-grid.rtl.css
mentor/static/mentor/vendor/bootstrap/css/bootstrap-grid.rtl.css.map
mentor/static/mentor/vendor/bootstrap/css/bootstrap-grid.rtl.min.css
mentor/static/mentor/vendor/bootstrap/css/bootstrap-grid.rtl.min.css.map
mentor/static/mentor/vendor/bootstrap/css/bootstrap-reboot.css
mentor/static/mentor/vendor/bootstrap/css/bootstrap-reboot.css.map
mentor/static/mentor/vendor/bootstrap/css/bootstrap-reboot.min.css
mentor/static/mentor/vendor/bootstrap/css/bootstrap-reboot.min.css.map
mentor/static/mentor/vendor/bootstrap/css/bootstrap-reboot.rtl.css
mentor/static/mentor/vendor/bootstrap/css/bootstrap-reboot.rtl.css.map
mentor/static/mentor/vendor/bootstrap/css/bootstrap-reboot.rtl.min.css
mentor/static/mentor/vendor/bootstrap/css/bootstrap-reboot.rtl.min.css.map
mentor/static/mentor/vendor/bootstrap/css/bootstrap-utilities.css
django_mentor_ds_myenglish-1.4.0.dist-info/LICENSE
django_mentor_ds_myenglish-1.4.0.dist-info/METADATA
django_mentor_ds_myenglish-1.4.0.dist-info/WHEEL
django_mentor_ds_myenglish-1.4.0.dist-info/top_level.txt
django_mentor_ds_myenglish-1.4.0.dist-info/RECORD
